ods_mkdocs_theme/__init__.py
ods_mkdocs_theme/mkdocs_theme.yml
ods_mkdocs_theme/assets/images/favicon.ico
ods_mkdocs_theme/assets/images/orange-logo.svg
ods_mkdocs_theme/assets/stylesheets/orange.css
ods_mkdocs_theme/partials/footer.html
ods_mkdocs_theme-0.1.1.dist-info/LICENSE
ods_mkdocs_theme-0.1.1.dist-info/METADATA
ods_mkdocs_theme-0.1.1.dist-info/NOTICE.txt
ods_mkdocs_theme-0.1.1.dist-info/WHEEL
ods_mkdocs_theme-0.1.1.dist-info/entry_points.txt
ods_mkdocs_theme-0.1.1.dist-info/top_level.txt
ods_mkdocs_theme-0.1.1.dist-info/RECORD
